<?xml version="1.0" encoding="windows-1252" ?>
<!DOCTYPE ViewLink SYSTEM "jbo_03_01.dtd">
<!---->
<ViewLink
  xmlns="http://xmlns.oracle.com/bc4j"
  Name="IssueRecWashLFkLink"
  Version="11.1.1.62.29"
  InheritPersonalization="true"
  EntityAssociation="mnj.mfg.model.entities.IssueRecWashLFkAssoc">
  <DesignTime>
    <Attr Name="_isCodegen" Value="true"/>
  </DesignTime>
  <ViewLinkDefEnd
    Name="HeaderVO"
    Cardinality="1"
    Owner="mnj.mfg.model.views.HeaderVO"
    Source="true">
    <DesignTime>
      <Attr Name="_finderName" Value="HeaderVO"/>
      <Attr Name="_isUpdateable" Value="true"/>
    </DesignTime>
    <AttrArray Name="Attributes">
      <Item Value="mnj.mfg.model.views.HeaderVO.HeaderId"/>
    </AttrArray>
  </ViewLinkDefEnd>
  <ViewLinkDefEnd
    Name="LineVO"
    Cardinality="-1"
    Owner="mnj.mfg.model.views.LineVO">
    <DesignTime>
      <Attr Name="_finderName" Value="LineVO"/>
      <Attr Name="_isUpdateable" Value="true"/>
    </DesignTime>
    <AttrArray Name="Attributes">
      <Item Value="mnj.mfg.model.views.LineVO.HeaderId"/>
    </AttrArray>
  </ViewLinkDefEnd>
</ViewLink>
